Workbook
Name _100_PV: #REF!
Name _100_SVI: #REF!
Name _1000_XM: #REF!
Name _145110: #REF!
Name _162460: [4]STEPHAN!$B$2:$P$71
Name _170_LIGHT: #REF!
Name _170_PV: #REF!
Name _171015: #REF!
Name _171064: #REF!
Name _171066: #REF!
Name _171068: #REF!
Name _171510: #REF!
Name _171562: #REF!
Name _172012: #REF!
Name _172020: #REF!
Name _172022: #REF!
Name _172062: #REF!
Name _172510: [4]STEPHAN!$B$2:$Q$71
Name _172610: [4]STEPHAN!$B$2:$Q$71
Name _176072: #REF!
Name A_impresión_IM: #REF!
Name bd: #REF!
Name bof: "ComboBox1"
Name dd: #REF!
Name EssLatest: "JAN"
Name EssLatest_10: "JAN"
Name EssLatest_11: "JAN"
Name EssLatest_12: "JAN"
Name EssLatest_13: "JAN"
Name EssLatest_14: "JAN"
Name EssLatest_15: "JAN"
Name EssLatest_16: "JAN"
Name EssLatest_18: "JAN"
Name EssLatest_2: "JANN0"
Name EssLatest_20: "YTDMM01"
Name EssLatest_25: "YTDMM01"
Name EssLatest_26: "YTDMM01"
Name EssLatest_3: "JANN0"
Name EssLatest_38: "JAN"
Name EssLatest_39: "JAN"
Name EssLatest_4: "JANN0"
Name EssLatest_47: "JAN"
Name EssLatest_48: "JAN"
Name EssLatest_5: "JANN0"
Name EssLatest_6: "YTDMM01"
Name EssLatest_7: "YTDMM01"
Name EssLatest_8: "YTDMM01"
Name EssLatest_9: "JAN"
Name EssOptions_10: "A3000001100130001011001101020_01 00"
Name EssOptions_11: "A3000001100130001011001101020_01 00"
Name EssOptions_12: "A3000001100130001011001101020_01 00"
Name EssOptions_13: "A3000001100130001011001101020_01 00"
Name EssOptions_14: "A3000001100130001011001101020_01 00"
Name EssOptions_15: "A3000001100130001011001101020_01 00"
Name EssOptions_16: "A3000001100130001011001101020_01 00"
Name EssOptions_18: "A3000001100130001011001101020_01 00"
Name EssOptions_2: "A1100000010121000011001111120_01000"
Name EssOptions_20: "A3100000000110001011011111020_01000"
Name EssOptions_25: "A3100000000130000000011100020_01000"
Name EssOptions_26: "A3100000000110001011011111020_01000"

Sheet Datos materia prima
A1: Datos de materia prima
A2: Coste de la leche en fabrica | B2: Presupuesto | C2: Real
A3: 1. Precio base | B3: 0.51 | C3: 0.51
A4: 2. Primas calidad (MG/MP) | B4: 0.027 | C4: 0.0155
A5: 3. Primas higiene | B5: 0.015 | C5: 0.007
A6: 4. Prima sostenibilidad | B6: 0.015 | C6: 0.015
A7: 5. Total precio al ganadero | B7: =SUM(B3:B6) -> 0.567 | C7: =SUM(C3:C6) -> 0.5475
A8: 6. Coste transporte + otros recogida | B8: 0.021 | C8: 0.025
A9: Total euros/L | B9: =SUM(B7:B8) -> 0.588 | C9: =SUM(C7:C8) -> 0.5725
A10: 7. Materia grasa | B10: =B27*B16/1000 -> 0.2352 | C10: =C27*C16/1000 -> 0.229
A11: 8. Proteína | B11: =B28*B17/1000 -> 0.3528 | C11: =C28*C17/1000 -> 0.3435
A12: Composición leche (% m/m)
A13: 9. Materia grasa | B13: 0.041 | C13: 0.0395
A14: 10. Proteinas totales | B14: 0.0345 | C14: 0.034
A15: Composición leche (g/L)
A16: 11. Materia grasa | B16: =B13*B21*1000 -> 42.403446 | C16: =C13*C21*1000 -> 40.852168
A17: 12. Proteinas totales | B17: =B14*B21*1000 -> 35.680948 | C17: =C14*C21*1000 -> 35.163892
A18: 13. Lactosa | B18: 48 | C18: 48
A19: 14. Sales minerales y otros | B19: 9 | C19: 9
A20: 15. Agua | B20: =B21*1000-SUM(B16:B19) -> 899.146 | C20: =C21*1000-SUM(C16:C19) -> 901.21604
A21: 16. Densidad | B21: =(-0.2307*10^(-2)*B22^2-0.2655*B22+1040.51-B13*(-0.478*10^(-4)*B22^2+0.969*10^(-2)*B22+0.967))/1000 -> 1.0342304 | C21: =(-0.2307*10^(-2)*C22^2-0.2655*C22+1040.51-C13*(-0.478*10^(-4)*C22^2+0.969*10^(-2)*C22+0.967))/1000 -> 1.0342321
A22: ⁰C medida | B22: 20 | C22: 20
A23: Valoración materia prima
A24: 17. Valoración MG | B24: 0.4 | C24: 0.4
A25: 18. Valoración MP | B25: =1-B24 -> 0.6 | C25: =1-C24 -> 0.6
A26: Precio resultante de la materia
A27: 19. Precio MG (euros/kg) | B27: =B9/B16*B24*1000 -> 5.546719 | C27: =C9/C16*C24*1000 -> 5.6055776
A28: 20. Precio MP (euros/kg) | B28: =B9/B17*B25*1000 -> 9.8876295 | C28: =C9/C17*C25*1000 -> 9.7685434

Sheet Estándar técnico
A1: Estándar de producto | B1: Vaca
A2: Fabricación, KG | B2: 1
A3: 1. Características del queso
A4: EST salida salado | B4: 0.52
A5: MG salida salado | B5: 0.27
A6: ESM | B6: =B4-B5 -> 0.25
A7: HFD | B7: =(1-B4)/(1-B5) -> 0.65753425
A8: G/ES | B8: =B5/B4 -> 0.51923077
A9: 2. Composición de la leche de fabricación
A10: Leche en cuba MG (g/L) | B10: 40.35
A11: Leche en cuba MP (g/L) | B11: 34.11
A12: 3. Datos tecnológicos
A13: Recup MP | B13: 0.92
A14: 4. Cálculos
A15: ESM queso obtenido a partir de MP leche (g/L) | B15: =B13*B11 -> 31.3812
A16: Litraje unitario | B16: =B6*1000/B15 -> 7.9665532
A17: MG teórica en la cuba (g/L) | B17: =B5*1000/B16 -> 33.891696
A18: Recup MG | B18: =B17/B10 -> 0.8399429
A19: MG pérdida bruta en suero (g/L) | B19: =B17-B10 -> -6.458304
A20: MG pérdida bruta en suero % | B20: =B19/B10 -> -0.1600571
A21: Consumo MG/kg queso | B21: =B10*B16 -> 321.45042
A22: Consumo MP/kg queso | B22: =B11*B16 -> 271.73913

Sheet Datos fabricación real
A1: Fabricación
A2: Datos de la fabricación real | B2: 45292
A3: Fabricación, KG | B3: 637.56
A4: EST a salida de sal (%) | B4: 0.4995
A5: MG a salida de sal (%) | B5: 0.2546
A6: Litros leche puestos en fab (cuba) | B6: 5025
A7: Composición leche MG (g/L) | B7: 41.07
A8: Composición leche MP (g/L) | B8: 33.95
A9: KMG puestos en fabricacion (cuba) | B9: =B7*B6/1000 -> 206.37675
A10: KMP puestos en fabricacion (cuba) | B10: =B8*B6/1000 -> 170.59875
A11: Utilización de nata de suero
A12: KMG Nata suero recuperada puesta en fab | B12: 0
A13: MG (% m/m) | B13: 0.4
A14: MG (g/L) | B14: =B13/100*B16*1000*100 -> 394
A15: MP (g/L) | B15: 5.91
A16: Densidad nata a 20 °C (kg/L) | B16: 0.985

Sheet Desviaciones
A1: Análisis de desviaciones | B1: Estándar | C1: Real
A2: Fabricación, KG | C2: ='Datos fabricación real'!B3 -> 637.56
A3: EST | B3: ='Estándar técnico'!B4 -> 0.52 | C3: ='Datos fabricación real'!B4 -> 0.4995
A4: MG | B4: ='Estándar técnico'!B5 -> 0.27 | C4: ='Datos fabricación real'!B5 -> 0.2546
A5: ESM | B5: =B3-B4 -> 0.25 | C5: =C3-C4 -> 0.2449
A6: HFD | B6: =(1-B3)/(1-B4) -> 0.65753425 | C6: =(1-C3)/(1-C4) -> 0.67145157
A7: G/ES | B7: =B4/B3 -> 0.51923077 | C7: =C4/C3 -> 0.50970971
A8: gr MG queso/kg queso | B8: =B4*1000 -> 270 | C8: =C4*1000 -> 254.6
A9: g ESM queso/kg queso | B9: =B5*1000 -> 250 | C9: =C5*1000 -> 244.9
A10: factor MG/MP queso | B10: =B8/B9 -> 1.08 | C10: =C8/C9 -> 1.039608
A11: Litros leche puestos en fab (cuba) | B11: =B15/B19*1000 -> 5079.1557 | C11: ='Datos fabricación real'!B6 -> 5025
A12: Composición leche en cuba MG (g/L) | B12: ='Estándar técnico'!B10 -> 40.35 | C12: =C14/C11*1000 -> 41.07
A13: Composición leche en cuba MP (g/L) | B13: ='Estándar técnico'!B11 -> 34.11 | C13: =C15/C11*1000 -> 33.95
A14: KMG puestos en fabricacion (cuba) | B14: =B$4/B$22*C$2 -> 204.94393 | C14: ='Datos fabricación real'!B9 -> 206.37675
A15: KMP puestos en fabricacion (cuba) | B15: =C$2*B$5/B$23 -> 173.25 | C15: ='Datos fabricación real'!B10 -> 170.59875
A16: KMG Nata suero recuperada puesta en fab | B16: =B11*B26/1000 -> 0 | C16: ='Datos fabricación real'!B12 -> 0
A17: factor MG/MP leche cubas | B17: =B14/B15 -> 1.1829376 | C17: =C14/C15 -> 1.2097202
A18: g MG/L leche en cuba | B18: =B12 -> 40.35 | C18: =C31*C2/C11 -> 41.07
A19: g MP/L leche en cuba | B19: =B13 -> 34.11 | C19: =C32*C2/C11 -> 33.95
A20: MG teórica en cuba g/L | B20: =B8/B21 -> 33.891696 | C20: =C8/C21 -> 32.30304
A21: Litraje unitario (L/Kg) | B21: =(B5*1000/B19)/B23 -> 7.9665532 | C21: =(C5*1000/C19)/C23 -> 7.8816111
A22: Recup MG | B22: ='Estándar técnico'!B18 -> 0.8399429 | C22: =(C4*C2)/C14 -> 0.78653616
A23: Recup MP | B23: ='Estándar técnico'!B13 -> 0.92 | C23: =C5*C2/C15 -> 0.91523791
A24: MG pérdida bruta (g/L) | B24: =B18-B20 -> 6.458304 | C24: =C18-C20 -> 8.76696
A25: MG pérdida bruta % | B25: =B24/B18 -> 0.1600571 | C25: =C24/C18 -> 0.21346384
A26: MG suero recuperada puesta en fab g/L | B26: 0 | C26: =C16*1000/C11 -> 0
A27: MG pérdida neta g/L | B27: =B24-B26 -> 6.458304 | C27: =C24-C26 -> 8.76696
A28: MG pérdida neta % | B28: =B27/B18 -> 0.1600571 | C28: =C27/C18 -> 0.21346384
A30: Consumos y desviaciones por consumo y precio | B30: Std | C30: Real | D30: Desv kg | E30: Desv total € | F30: Desv € /kg
A31: Consumo g MG/kg queso | B31: =B14/C2*1000 -> 321.45042 | C31: =C14/C2*1000 -> 323.69777 | D31: =(B31-C31)*C2/1000 -> -1.4328186 | E31: =D31*B34 -> -7.9478448 | F31: =E31/C2 -> -0.012466034
A32: Consumo g MP/kg queso | B32: =B15/C2*1000 -> 271.73913 | C32: =C15/C2*1000 -> 267.5807 | D32: =(B32-C32)*C2/1000 -> 2.65125 | E32: =D32*B35 -> 26.21556 | F32: =E32/C2 -> 0.041118577
A33: Total desviaciones por consumo | E33: =SUM(E31:E32) -> 18.267715 | F33: =SUM(F31:F32) -> 0.028652543
A34: Coste MG (euros/kg) | B34: 5.547 | C34: 5.606 | E34: =(B34-C34)*C2 -> -37.61604 | F34: =E34/C2 -> -0.059
A35: Coste MP (euros/kg) | B35: 9.888 | C35: 9.769 | E35: =(B35-C35)*C2 -> 75.86964 | F35: =E35/C2 -> 0.119
A36: Total desviaciones por precio | E36: =SUM(E34:E35) -> 38.2536 | F36: =E36/C2 -> 0.06
A38: Desviaciones por componente de materia prima | B38: Std | C38: Real | D38: Dif | E38: Desv total € | F38: Desv € /kg
A39: MG leche cuba | B39: =B14 -> 204.94393 | C39: =C14 -> 206.37675 | D39: =B39-C39 -> -1.4328186 | E39: =D39*B34 -> -7.9478448 | F39: =E39/C2 -> -0.012466034
A40: MP leche cuba | B40: =B15 -> 173.25 | C40: =C15 -> 170.59875 | D40: =B40-C40 -> 2.65125 | E40: =D40*B35 -> 26.21556 | F40: =E40/C2 -> 0.041118577
E41: =SUM(E39:E40) -> 18.267715 | F41: =SUM(F39:F40) -> 0.028652543
A43: Desviaciones por composición queso + tecnología | B43: Std | C43: Real | D43: Desv kg | E43: Desv total € | F43: Desv € /kg
A44: MG
A45: Efecto EST (composición MG) | B45: =B$4/B$22*C$2 -> 204.94393 | C45: =(C$4/B$22)*C$2 -> 193.25454 | D45: =B45-C45 -> 11.689395 | E45: =D45*B$34 -> 64.841072 | F45: =E45/$C$2 -> 0.10170191
A46: Efecto rendimiento (recup MG) | B46: =B$4/B$22*C$2 -> 204.94393 | C46: =(B$4/C$22)*C$2 -> 218.85987 | D46: =B46-C46 -> -13.915937 | E46: =D46*B$34 -> -77.191703 | F46: =E46/$C$2 -> -0.12107363
A47: Otros efectos no explicados | D47: =(B22-C22)*(B4-C4)*C2 -> 0.52437004 | E47: =D47*B$34 -> 2.9086806 | F47: =E47/$C$2 -> 0.0045622068
A48: Total MG | D48: =SUM(D45:D47) -> -1.7021724 | E48: =SUM(E45:E47) -> -9.4419502 | F48: =E48/$C$2 -> -0.014809508
A49: ESM
A50: Efecto EST (composición ESM) | B50: =C$2*B$5/B$23 -> 173.25 | C50: =C2*C5/B23 -> 169.7157 | D50: =B50-C50 -> 3.5343 | E50: =D50*B$35 -> 34.947158 | F50: =E50/$C$2 -> 0.054813913
A51: Efecto rendimiento (recup MP) | B51: =C$2*B$5/B$23 -> 173.25 | C51: =C2*B5/C23 -> 174.15144 | D51: =B51-C51 -> -0.90143936 | E51: =D51*B$35 -> -8.9134324 | F51: =E51/$C$2 -> -0.013980539
A52: Otros efectos no explicados | D52: =(B23-C23)*(B5-C5)*C2 -> 0.015484191 | E52: =D52*B$35 -> 0.15310768 | F52: =E52/$C$2 -> 0.00024014631
A53: Total MP | D53: =SUM(D50:D52) -> 2.6483448 | E53: =SUM(E50:E52) -> 26.186834 | F53: =E53/$C$2 -> 0.04107352
A54: Total explicado | E54: =E53+E48 -> 16.744883 | F54: =F53+F48 -> 0.026264012
A55: EST (MG + ESM) | E55: =SUM(E45,E50) -> 99.78823 | F55: =E55/$C$2 -> 0.15651583
A56: Recuperación materia (MG+MP) | E56: =SUM(E46,E51) -> -86.105135 | F56: =E56/$C$2 -> -0.13505417
A57: Otros efectos no explicados | E57: =SUM(E47+E52) -> 3.0617883 | F57: =E57/$C$2 -> 0.0048023531
A58: Total explicado por composición queso + tecnología | E58: =1-ABS(E57/E54) -> 0.81715082
