Workbook
Name _100_PV: #REF!
Name _100_SVI: #REF!
Name _1000_XM: #REF!
Name _145110: #REF!
Name _162460: [4]STEPHAN!$B$2:$P$71
Name _170_LIGHT: #REF!
Name _170_PV: #REF!
Name _171015: #REF!
Name _171064: #REF!
Name _171066: #REF!
Name _171068: #REF!
Name _171510: #REF!
Name _171562: #REF!
Name _172012: #REF!
Name _172020: #REF!
Name _172022: #REF!
Name _172062: #REF!
Name _172510: [4]STEPHAN!$B$2:$Q$71
Name _172610: [4]STEPHAN!$B$2:$Q$71
Name _176072: #REF!
Name A_impresión_IM: #REF!
Name bd: #REF!
Name bof: "ComboBox1"
Name dd: #REF!
Name EssLatest: "JAN"
Name EssLatest_10: "JAN"
Name EssLatest_11: "JAN"
Name EssLatest_12: "JAN"
Name EssLatest_13: "JAN"
Name EssLatest_14: "JAN"
Name EssLatest_15: "JAN"
Name EssLatest_16: "JAN"
Name EssLatest_18: "JAN"
Name EssLatest_2: "JANN0"
Name EssLatest_20: "YTDMM01"
Name EssLatest_25: "YTDMM01"
Name EssLatest_26: "YTDMM01"
Name EssLatest_3: "JANN0"
Name EssLatest_38: "JAN"
Name EssLatest_39: "JAN"
Name EssLatest_4: "JANN0"
Name EssLatest_47: "JAN"
Name EssLatest_48: "JAN"
Name EssLatest_5: "JANN0"
Name EssLatest_6: "YTDMM01"
Name EssLatest_7: "YTDMM01"
Name EssLatest_8: "YTDMM01"
Name EssLatest_9: "JAN"
Name EssOptions_10: "A3000001100130001011001101020_01 00"
Name EssOptions_11: "A3000001100130001011001101020_01 00"
Name EssOptions_12: "A3000001100130001011001101020_01 00"
Name EssOptions_13: "A3000001100130001011001101020_01 00"
Name EssOptions_14: "A3000001100130001011001101020_01 00"
Name EssOptions_15: "A3000001100130001011001101020_01 00"
Name EssOptions_16: "A3000001100130001011001101020_01 00"
Name EssOptions_18: "A3000001100130001011001101020_01 00"
Name EssOptions_2: "A1100000010121000011001111120_01000"
Name EssOptions_20: "A3100000000110001011011111020_01000"
Name EssOptions_25: "A3100000000130000000011100020_01000"
Name EssOptions_26: "A3100000000110001011011111020_01000"

Sheet Datos de partida
A1: 1. Presupuesto | B1: Modelo
A2: Datos del producto
A3: EST a salida de sal (%) | B3: 0.55
A4: MG a saida de sal (%) | B4: 0.28
A5: Coste de la leche en fabrica
A6: Precio pagado al ganadero (euros/L) | B6: 0.362
A7: Coste transporte + otros recogida (euros/L) | B7: 0.021
A8: Total euros/L | B8: =SUM(B6:B7) -> 0.383
A9: Reparto precio MG leche | B9: 0.5
A10: Reparto precio MP leche (1 - MG) | B10: =1-B9 -> 0.5
A11: Valor MG leche en fábrica (euros/L) | B11: =B30*B18/1000 -> 0.1915
A12: Valor MP leche en fábrica (euros/L) | B12: =B31*B19/1000 -> 0.1915
A13: Datos de materia prima
A14: Composición leche
A15: Materia grasa (% m/m) | B15: 0.0376
A16: Proteinas totales (% m/m) | B16: 0.0326
A17: Factor MG/MP | B17: =B15/B16 -> 1.1533742
A18: Materia grasa (g/L) | B18: =B15*B24 -> 38.887209
A19: Proteinas totales (g/L) | B19: =B16*B24 -> 33.716037
A20: Lactosa | B20: 48
A21: Sales minerales y otros | B21: 9
A22: Agua | B22: =B24-SUM(B18:B21) -> 904.63103
A23: Temperatura a la que se hace la medida (⁰C) | B23: 20
A24: Densidad | B24: =-0.2307*10^(-2)*B23^2-0.2655*B23+1040.51-B15*(-0.478*10^(-4)*B23^2+0.969*10^(-2)*B23+0.967) -> 1034.2343
A25: Composición nata suero (g/L)
A26: Materia grasa (% m/m) | B26: 0.43
A27: MG | B27: =B26*B40*1000 -> 423.62953
A28: MP | B28: 5.91
A29: Precio materia (euros/kg)
A30: MG | B30: =B8/B18*B9*1000 -> 4.9244985
A31: MP | B31: =B8/B19*B10*1000 -> 5.6797897
A32: Datos estándar
A33: Receta en volumen (debe sumar 100%)
A34: Leche (%) | B34: 1
A35: Nata de suero de recuperación (%) | B35: =1-B34 -> 0
A36: Coeficientes de recuperación
A37: Coef de recuperación MG
A38: Coef de recuperación MP | B38: 0.9465
A39: Otros datos
A40: Densidad nata (kg/L) | B40: =(-0.2307*10^(-2)*B23^2-0.2655*B23+1040.51-B26*100*(-0.478*10^(-4)*B23^2+0.969*10^(-2)*B23+0.967))/1000 -> 0.98518496
A42: 2. Estándar técnico del producto
A43: Análisis salida sal
A44: EST % | B44: ='Datos de partida'!B3 -> 0.55
A45: MG | B45: ='Datos de partida'!B4 -> 0.28
A46: G/ES % | B46: =B45/B44 -> 0.50909091
A47: HFD | B47: =(1-B44)/(1-B44*B46) -> 0.625
A48: ESM | B48: =B44-B45 -> 0.27
A50: MP en cuba (g/L) | B50: =B88 -> 33.716037
A51: Ratio recuperación MP (Rendimiento MP %) | B51: ='Datos de partida'!B38 -> 0.9465
A52: Ratio recuperación MG (%) | B52: =B55/B58 -> 0.85102955
A53: Coef G (ESM queso obtenido a partir de MP leche) | B53: =B51*B50 -> 31.912229
A54: Litraje unitario | B54: =B48*1000/B53 -> 8.4607063
A55: MG teórica en la cuba (g/L) | B55: =B45*1000/B54 -> 33.094164
A56: MG Pérddias brutas suero (g/L) | B56: =B58-B55 -> 5.7930449
A57: MG Pérddias brutas suero (%) | B57: =B56/B58 -> 0.14897045
A58: MG estándar en la mezcla (g/L) | B58: =B85 -> 38.887209
A59: Consumo MG total leche en cuba | B59: =B58*B54 -> 329.01325
A60: Consumo MP total leche en cuba | B60: =B50*B54 -> 285.26149
A61: MG suero en cuba (g/L) | B61: =+B94/B54 -> 0
A62: MG Pérddas suero neta (g/L) | B62: =B56-B61 -> 5.7930449
A63: MG Pérddas suero neta (%) | B63: =+B62/B58 -> 0.14897045
A64: MG STD sin nata de suero (g/L) | B64: =+B58-B61 -> 38.887209
A65: Consumo MG (sólo MG comprada) (g/K queso) | B65: =B$64*B$54 -> 329.01325
A66: Consumo MP (sólo MP comprada) (g/K queso) | B66: =B$50*B$54 -> 285.26149
A67: Receta
A68: % Leche | B68: ='Datos de partida'!B34 -> 1
A69: % Nata de suero | B69: ='Datos de partida'!B35 -> 0
B70: =SUM(B68:B69) -> 1
A71: Composición leche
A72: MG Leche (g/L) | B72: ='Datos de partida'!B18 -> 38.887209
A73: MG Nata de Suero (g/L) | B73: ='Datos de partida'!B27 -> 423.62953
A75: MP Leche (g/L) | B75: ='Datos de partida'!B19 -> 33.716037
A76: MP Nata de suero (g/L) | B76: ='Datos de partida'!B28 -> 5.91
A78: Ratio MG/MP leche | B78: =+B85/B88 -> 1.1533742
A80: Densidad Leche | B80: ='Datos de partida'!B24/1000 -> 1.0342343
A81: Densidad Nata de suero | B81: ='Datos de partida'!B40 -> 0.98518496
A82: Leche en cubas
A83: MG Leche (g/L) | B83: =(B72*B68) -> 38.887209
A84: MG Nata de suero (g/L) | B84: =(B73*B69) -> 0
B85: =SUM(B83:B84) -> 38.887209
A86: MP Leche (g/L) | B86: =B75*B68 -> 33.716037
A87: MP Nata de suero (g/L) | B87: =B76*B69 -> 0
B88: =SUM(B86:B87) -> 33.716037
A89: Densidad calculada leche en cuba | B89: =SUMPRODUCT(B80:B81,B68:B69) -> 1.0342343
A91: Consumo materia g/kg queso
A92: MG Origen Leche | B92: =+B59*(B83)/B85 -> 329.01325
A93: MP Origen Leche | B93: =+B60*(B86)/B88 -> 285.26149
A94: MG Origen Nata Suero | B94: =+B$59*(B84)/B$85 -> 0
A95: MP Origen Nata Suero | B95: =+B$60*(B87)/B$88 -> 0
A96: Precio materia (euros/kg)
A97: MG | B97: ='Datos de partida'!B30 -> 4.9244985
A98: MP | B98: ='Datos de partida'!B31 -> 5.6797897
A99: VALOR MG | B99: =B92*B97/1000 -> 1.6202253
A100: VALOR MP | B100: =B93*B98/1000 -> 1.6202253
A101: Total mat prima | B101: =SUM(B99:B100) -> 3.2404505

Sheet Ejemplo
A1: 1. Presupuesto | B1: Modelo | D1: Ejemplo 1 Paso 1 | E1: Ejemplo 1 Paso 2 - MG/ES | F1: Ejemplo 1 Paso 3- Precio | H1: Ejemplo 3 Estandarización MG | I1: Ejemplo 3 Estandarización MG y precio
A2: Datos del producto
A3: EST a salida de sal (%) | B3: 0.55 | D3: 0.55 | E3: 0.55 | F3: 0.55 | H3: 0.55 | I3: 0.55
A4: MG a saida de sal (%) | B4: 0.28 | D4: 0.28 | E4: 0.268 | F4: 0.268 | H4: 0.28 | I4: 0.28
A5: Coste de la leche en fabrica
A6: Precio pagado al ganadero (euros/L) | B6: 0.362 | D6: 0.362 | E6: 0.362 | F6: 0.329 | H6: 0.362 | I6: 0.345
A7: Coste transporte + otros recogida (euros/L) | B7: 0.021 | D7: 0.021 | E7: 0.021 | F7: 0.021 | H7: 0.021 | I7: 0.021
A8: Total euros/L | B8: =SUM(B6:B7) -> 0.383 | D8: =SUM(D6:D7) -> 0.383 | E8: =SUM(E6:E7) -> 0.383 | F8: =SUM(F6:F7) -> 0.35 | H8: =SUM(H6:H7) -> 0.383 | I8: =SUM(I6:I7) -> 0.366
A10: Reparto precio MG leche | B10: 0.5 | D10: 0.5 | E10: 0.5 | F10: 0.5 | H10: 0.5 | I10: 0.5
A11: Reparto precio MP leche (1 - MG) | B11: =1-B10 -> 0.5 | D11: =1-D10 -> 0.5 | E11: =1-E10 -> 0.5 | F11: =1-F10 -> 0.5 | H11: =1-H10 -> 0.5 | I11: =1-I10 -> 0.5
A12: Valor MG leche en fábrica (euros/L) | B12: =B31*B19/1000 -> 0.1915 | D12: =D31*D19/1000 -> 0.1915 | E12: =E31*E19/1000 -> 0.1915 | F12: =F31*F19/1000 -> 0.175 | H12: =H31*H19/1000 -> 0.1915 | I12: =I31*I19/1000 -> 0.183
A13: Valor MP leche en fábrica (euros/L) | B13: =B32*B20/1000 -> 0.1915 | D13: =D32*D20/1000 -> 0.1915 | E13: =E32*E20/1000 -> 0.1915 | F13: =F32*F20/1000 -> 0.175 | H13: =H32*H20/1000 -> 0.1915 | I13: =I32*I20/1000 -> 0.183
A14: Datos de materia prima
A15: Composición leche
A16: Materia grasa (% m/m) | B16: 0.0376 | D16: 0.0336 | E16: 0.0336 | F16: 0.0336 | H16: 0.0359 | I16: 0.0359
A17: Proteinas totales (% m/m) | B17: 0.0326 | D17: 0.0311 | E17: 0.0311 | F17: 0.0311 | H17: 0.0311 | I17: 0.0311
A18: Factor MG/MP | B18: =B16/B17 -> 1.1533742 | D18: =D16/D17 -> 1.0803859 | E18: =E16/E17 -> 1.0803859 | F18: =F16/F17 -> 1.0803859 | H18: =H16/H17 -> 1.1543408 | I18: =I16/I17 -> 1.1543408
A19: Materia grasa (g/L) | B19: =B16*B25 -> 38.887209 | D19: =D16*D25 -> 34.750425 | E19: =E16*E25 -> 34.750425 | F19: =F16*F25 -> 34.750425 | H19: =H16*H25 -> 37.12908 | I19: =I16*I25 -> 37.12908
A20: Proteinas totales (g/L) | B20: =B17*B25 -> 33.716037 | D20: =D17*D25 -> 32.164828 | E20: =E17*E25 -> 32.164828 | F20: =F17*F25 -> 32.164828 | H20: =H17*H25 -> 32.164746 | I20: =I17*I25 -> 32.164746
A21: Lactosa | B21: 48 | D21: 48 | E21: 48 | F21: 48 | H21: 48 | I21: 48
A22: Sales minerales y otros | B22: 9 | D22: 9 | E22: 9 | F22: 9 | H22: 9 | I22: 9
A23: Agua | B23: =B25-SUM(B19:B22) -> 904.63103 | D23: =D25-SUM(D19:D22) -> 910.32359 | E23: =E25-SUM(E19:E22) -> 910.32359 | F23: =F25-SUM(F19:F22) -> 910.32359 | H23: =H25-SUM(H19:H22) -> 907.94239 | I23: =I25-SUM(I19:I22) -> 907.94239
A24: Temperatura a la que se hace la medida (⁰C) | B24: 20 | D24: 20 | E24: 20 | F24: 20 | H24: 20 | I24: 20
A25: Densidad | B25: =-0.2307*10^(-2)*B24^2-0.2655*B24+1040.51-B16*(-0.478*10^(-4)*B24^2+0.969*10^(-2)*B24+0.967) -> 1034.2343 | D25: =-0.2307*10^(-2)*D24^2-0.2655*D24+1040.51-D16*(-0.478*10^(-4)*D24^2+0.969*10^(-2)*D24+0.967) -> 1034.2388 | E25: =-0.2307*10^(-2)*E24^2-0.2655*E24+1040.51-E16*(-0.478*10^(-4)*E24^2+0.969*10^(-2)*E24+0.967) -> 1034.2388 | F25: =-0.2307*10^(-2)*F24^2-0.2655*F24+1040.51-F16*(-0.478*10^(-4)*F24^2+0.969*10^(-2)*F24+0.967) -> 1034.2388 | H25: =-0.2307*10^(-2)*H24^2-0.2655*H24+1040.51-H16*(-0.478*10^(-4)*H24^2+0.969*10^(-2)*H24+0.967) -> 1034.2362 | I25: =-0.2307*10^(-2)*I24^2-0.2655*I24+1040.51-I16*(-0.478*10^(-4)*I24^2+0.969*10^(-2)*I24+0.967) -> 1034.2362
A26: Composición nata suero (g/L)
A27: Materia grasa (% m/m) | B27: 0.43 | D27: 0.43 | E27: 0.4102 | F27: 0.4102 | H27: 0.4102 | I27: 0.4102
A28: MG | B28: =B27*B41*1000 -> 423.62953 | D28: =D27*D41*1000 -> 423.62953 | E28: =E27*E41*1000 -> 405.05014 | F28: =F27*F41*1000 -> 405.05014 | H28: =H27*H41*1000 -> 405.05014 | I28: =I27*I41*1000 -> 405.05014
A29: MP | B29: 5.91 | D29: 5.91 | E29: 1.67 | F29: 1.67 | H29: 1.67 | I29: 1.67
A30: Precio materia (euros/kg)
A31: MG | B31: =B8/B19*B10*1000 -> 4.9244985 | D31: =D8/D19*D10*1000 -> 5.510724 | E31: =E8/E19*E10*1000 -> 5.510724 | F31: =F8/F19*F10*1000 -> 5.0359096 | H31: =H8/H19*H10*1000 -> 5.1576823 | I31: =I8/I19*I10*1000 -> 4.9287513
A32: MP | B32: =B8/B20*B11*1000 -> 5.6797897 | D32: =D8/D20*D11*1000 -> 5.9537082 | E32: =E8/E20*E11*1000 -> 5.9537082 | F32: =F8/F20*F11*1000 -> 5.4407255 | H32: =H8/H20*H11*1000 -> 5.9537233 | I32: =I8/I20*I11*1000 -> 5.6894588
A33: Datos estándar
A34: Receta en volumen (debe sumar 100%)
A35: Leche (%) | B35: 1 | D35: 1 | E35: 1 | F35: 1 | H35: 1 | I35: 1
A36: Nata de suero de recuperación (%) | B36: =1-B35 -> 0 | D36: =1-D35 -> 0 | E36: =1-E35 -> 0 | F36: =1-F35 -> 0 | H36: =1-H35 -> 0 | I36: =1-I35 -> 0
A37: Coeficientes de recuperación
A38: Coef de recuperación MG
A39: Coef de recuperación MP | B39: 0.9465 | D39: 0.9465 | E39: 0.9465 | F39: 0.9465 | H39: 0.9465 | I39: 0.9465
A40: Otros datos
A41: Densidad nata (kg/L) | B41: =(-0.2307*10^(-2)*B24^2-0.2655*B24+1040.51-B27*100*(-0.478*10^(-4)*B24^2+0.969*10^(-2)*B24+0.967))/1000 -> 0.98518496 | D41: =(-0.2307*10^(-2)*D24^2-0.2655*D24+1040.51-D27*100*(-0.478*10^(-4)*D24^2+0.969*10^(-2)*D24+0.967))/1000 -> 0.98518496 | E41: =(-0.2307*10^(-2)*E24^2-0.2655*E24+1040.51-E27*100*(-0.478*10^(-4)*E24^2+0.969*10^(-2)*E24+0.967))/1000 -> 0.98744549 | F41: =(-0.2307*10^(-2)*F24^2-0.2655*F24+1040.51-F27*100*(-0.478*10^(-4)*F24^2+0.969*10^(-2)*F24+0.967))/1000 -> 0.98744549 | H41: =(-0.2307*10^(-2)*H24^2-0.2655*H24+1040.51-H27*100*(-0.478*10^(-4)*H24^2+0.969*10^(-2)*H24+0.967))/1000 -> 0.98744549 | I41: =(-0.2307*10^(-2)*I24^2-0.2655*I24+1040.51-I27*100*(-0.478*10^(-4)*I24^2+0.969*10^(-2)*I24+0.967))/1000 -> 0.98744549
A43: 2. Estándar técnico del producto
A44: Análisis salida sal
A45: EST % | B45: =Ejemplo!B3 -> 0.55 | D45: =Ejemplo!D3 -> 0.55 | E45: =Ejemplo!E3 -> 0.55 | F45: =Ejemplo!F3 -> 0.55 | H45: =Ejemplo!H3 -> 0.55 | I45: =Ejemplo!I3 -> 0.55
A46: MG | B46: =Ejemplo!B4 -> 0.28 | D46: =Ejemplo!D4 -> 0.28 | E46: =Ejemplo!E4 -> 0.268 | F46: =Ejemplo!F4 -> 0.268 | H46: =Ejemplo!H4 -> 0.28 | I46: =Ejemplo!I4 -> 0.28
A47: G/ES % | B47: =B46/B45 -> 0.50909091 | D47: =D46/D45 -> 0.50909091 | E47: =E46/E45 -> 0.48727273 | F47: =F46/F45 -> 0.48727273 | H47: =H46/H45 -> 0.50909091 | I47: =I46/I45 -> 0.50909091
A48: HFD | B48: =(1-B45)/(1-B45*B47) -> 0.625 | D48: =(1-D45)/(1-D45*D47) -> 0.625 | E48: =(1-E45)/(1-E45*E47) -> 0.6147541 | F48: =(1-F45)/(1-F45*F47) -> 0.6147541 | H48: =(1-H45)/(1-H45*H47) -> 0.625 | I48: =(1-I45)/(1-I45*I47) -> 0.625
A49: ESM | B49: =B45-B46 -> 0.27 | D49: =D45-D46 -> 0.27 | E49: =E45-E46 -> 0.282 | F49: =F45-F46 -> 0.282 | H49: =H45-H46 -> 0.27 | I49: =I45-I46 -> 0.27
A51: MP en cuba (g/L) | B51: =B89 -> 33.716037 | D51: =D89 -> 32.164828 | E51: =E89 -> 32.164828 | F51: =F89 -> 32.164828 | H51: =H89 -> 32.164746 | I51: =I89 -> 32.164746
A52: Ratio recuperación MP (Rendimiento MP %) | B52: =Ejemplo!B39 -> 0.9465 | D52: =Ejemplo!D39 -> 0.9465 | E52: =Ejemplo!E39 -> 0.9465 | F52: =Ejemplo!F39 -> 0.9465 | H52: =Ejemplo!H39 -> 0.9465 | I52: =Ejemplo!I39 -> 0.9465
A53: Ratio recuperación MG (%) | B53: =B56/B59 -> 0.85102955 | D53: =D56/D59 -> 0.90852315 | E53: =E56/E59 -> 0.83258276 | F53: =F56/F59 -> 0.83258276 | H53: =H56/H59 -> 0.85031693 | I53: =I56/I59 -> 0.85031693
A54: Coef G (ESM queso obtenido a partir de MP leche) | B54: =B52*B51 -> 31.912229 | D54: =D52*D51 -> 30.44401 | E54: =E52*E51 -> 30.44401 | F54: =F52*F51 -> 30.44401 | H54: =H52*H51 -> 30.443932 | I54: =I52*I51 -> 30.443932
A55: Litraje unitario | B55: =B49*1000/B54 -> 8.4607063 | D55: =D49*1000/D54 -> 8.8687398 | E55: =E49*1000/E54 -> 9.262906 | F55: =F49*1000/F54 -> 9.262906 | H55: =H49*1000/H54 -> 8.8687623 | I55: =I49*1000/I54 -> 8.8687623
A56: MG teórica en la cuba (g/L) | B56: =B46*1000/B55 -> 33.094164 | D56: =D46*1000/D55 -> 31.571566 | E56: =E46*1000/E55 -> 28.932605 | F56: =F46*1000/F55 -> 28.932605 | H56: =H46*1000/H55 -> 31.571485 | I56: =I46*1000/I55 -> 31.571485
A57: MG Pérddias brutas suero (g/L) | B57: =B59-B56 -> 5.7930449 | D57: =D59-D56 -> 3.1788595 | E57: =E59-E56 -> 5.8178201 | F57: =F59-F56 -> 5.8178201 | H57: =H59-H56 -> 5.5575947 | I57: =I59-I56 -> 5.5575947
A58: MG Pérddias brutas suero (%) | B58: =B57/B59 -> 0.14897045 | D58: =D57/D59 -> 0.091476852 | E58: =E57/E59 -> 0.16741724 | F58: =F57/F59 -> 0.16741724 | H58: =H57/H59 -> 0.14968307 | I58: =I57/I59 -> 0.14968307
A59: MG estándar en la mezcla (g/L) | B59: =B86 -> 38.887209 | D59: =D86 -> 34.750425 | E59: =E86 -> 34.750425 | F59: =F86 -> 34.750425 | H59: =H86 -> 37.12908 | I59: =I86 -> 37.12908
A60: Consumo MG total leche en cuba | B60: =B59*B55 -> 329.01325 | D60: =D59*D55 -> 308.19248 | E60: =E59*E55 -> 321.88992 | F60: =F59*F55 -> 321.88992 | H60: =H59*H55 -> 329.28899 | I60: =I59*I55 -> 329.28899
A61: Consumo MP total leche en cuba | B61: =B51*B55 -> 285.26149 | D61: =D51*D55 -> 285.26149 | E61: =E51*E55 -> 297.93978 | F61: =F51*F55 -> 297.93978 | H61: =H51*H55 -> 285.26149 | I61: =I51*I55 -> 285.26149
A62: MG suero en cuba (g/L) | B62: =+B95/B55 -> 0 | D62: =+D95/D55 -> 0 | E62: =+E95/E55 -> 0 | F62: =+F95/F55 -> 0 | H62: =+H95/H55 -> 0 | I62: =+I95/I55 -> 0
A63: MG Pérddas suero neta (g/L) | B63: =B57-B62 -> 5.7930449 | D63: =D57-D62 -> 3.1788595 | E63: =E57-E62 -> 5.8178201 | F63: =F57-F62 -> 5.8178201 | H63: =H57-H62 -> 5.5575947 | I63: =I57-I62 -> 5.5575947
A64: MG Pérddas suero neta (%) | B64: =+B63/B59 -> 0.14897045 | D64: =+D63/D59 -> 0.091476852 | E64: =+E63/E59 -> 0.16741724 | F64: =+F63/F59 -> 0.16741724 | H64: =+H63/H59 -> 0.14968307 | I64: =+I63/I59 -> 0.14968307
A65: MG STD sin nata de suero (g/L) | B65: =+B59-B62 -> 38.887209 | D65: =+D59-D62 -> 34.750425 | E65: =+E59-E62 -> 34.750425 | F65: =+F59-F62 -> 34.750425 | H65: =+H59-H62 -> 37.12908 | I65: =+I59-I62 -> 37.12908
A66: Consumo MG (sólo MG comprada) (g/K queso) | B66: =B$65*B$55 -> 329.01325 | D66: =D$65*D$55 -> 308.19248 | E66: =E$65*E$55 -> 321.88992 | F66: =F$65*F$55 -> 321.88992 | H66: =H$65*H$55 -> 329.28899 | I66: =I$65*I$55 -> 329.28899
A67: Consumo MP (sólo MP comprada) (g/K queso) | B67: =B$51*B$55 -> 285.26149 | D67: =D$51*D$55 -> 285.26149 | E67: =E$51*E$55 -> 297.93978 | F67: =F$51*F$55 -> 297.93978 | H67: =H$51*H$55 -> 285.26149 | I67: =I$51*I$55 -> 285.26149
A68: Receta
A69: % Leche | B69: =Ejemplo!B35 -> 1 | D69: =Ejemplo!D35 -> 1 | E69: =Ejemplo!E35 -> 1 | F69: =Ejemplo!F35 -> 1 | H69: =Ejemplo!H35 -> 1 | I69: =Ejemplo!I35 -> 1
A70: % Nata de suero | B70: =Ejemplo!B36 -> 0 | D70: =Ejemplo!D36 -> 0 | E70: =Ejemplo!E36 -> 0 | F70: =Ejemplo!F36 -> 0 | H70: =Ejemplo!H36 -> 0 | I70: =Ejemplo!I36 -> 0
B71: =SUM(B69:B70) -> 1 | D71: =SUM(D69:D70) -> 1 | E71: =SUM(E69:E70) -> 1 | F71: =SUM(F69:F70) -> 1 | H71: =SUM(H69:H70) -> 1 | I71: =SUM(I69:I70) -> 1
A72: Composición leche
A73: MG Leche (g/L) | B73: =Ejemplo!B19 -> 38.887209 | D73: =Ejemplo!D19 -> 34.750425 | E73: =Ejemplo!E19 -> 34.750425 | F73: =Ejemplo!F19 -> 34.750425 | H73: =Ejemplo!H19 -> 37.12908 | I73: =Ejemplo!I19 -> 37.12908
A74: MG Nata de Suero (g/L) | B74: =Ejemplo!B28 -> 423.62953 | D74: =Ejemplo!D28 -> 423.62953 | E74: =Ejemplo!E28 -> 405.05014 | F74: =Ejemplo!F28 -> 405.05014 | H74: =Ejemplo!H28 -> 405.05014 | I74: =Ejemplo!I28 -> 405.05014
A76: MP Leche (g/L) | B76: =Ejemplo!B20 -> 33.716037 | D76: =Ejemplo!D20 -> 32.164828 | E76: =Ejemplo!E20 -> 32.164828 | F76: =Ejemplo!F20 -> 32.164828 | H76: =Ejemplo!H20 -> 32.164746 | I76: =Ejemplo!I20 -> 32.164746
A77: MP Nata de suero (g/L) | B77: =Ejemplo!B29 -> 5.91 | D77: =Ejemplo!D29 -> 5.91 | E77: =Ejemplo!E29 -> 1.67 | F77: =Ejemplo!F29 -> 1.67 | H77: =Ejemplo!H29 -> 1.67 | I77: =Ejemplo!I29 -> 1.67
A79: Ratio MG/MP leche | B79: =+B86/B89 -> 1.1533742 | D79: =+D86/D89 -> 1.0803859 | E79: =+E86/E89 -> 1.0803859 | F79: =+F86/F89 -> 1.0803859 | H79: =+H86/H89 -> 1.1543408 | I79: =+I86/I89 -> 1.1543408
A81: Densidad Leche | B81: =Ejemplo!B25/1000 -> 1.0342343 | D81: =Ejemplo!D25/1000 -> 1.0342388 | E81: =Ejemplo!E25/1000 -> 1.0342388 | F81: =Ejemplo!F25/1000 -> 1.0342388 | H81: =Ejemplo!H25/1000 -> 1.0342362 | I81: =Ejemplo!I25/1000 -> 1.0342362
A82: Densidad Nata de suero | B82: =Ejemplo!B41 -> 0.98518496 | D82: =Ejemplo!D41 -> 0.98518496 | E82: =Ejemplo!E41 -> 0.98744549 | F82: =Ejemplo!F41 -> 0.98744549 | H82: =Ejemplo!H41 -> 0.98744549 | I82: =Ejemplo!I41 -> 0.98744549
A83: Leche en cubas
A84: MG Leche (g/L) | B84: =(B73*B69) -> 38.887209 | D84: =(D73*D69) -> 34.750425 | E84: =(E73*E69) -> 34.750425 | F84: =(F73*F69) -> 34.750425 | H84: =(H73*H69) -> 37.12908 | I84: =(I73*I69) -> 37.12908
A85: MG Nata de suero (g/L) | B85: =(B74*B70) -> 0 | D85: =(D74*D70) -> 0 | E85: =(E74*E70) -> 0 | F85: =(F74*F70) -> 0 | H85: =(H74*H70) -> 0 | I85: =(I74*I70) -> 0
B86: =SUM(B84:B85) -> 38.887209 | D86: =SUM(D84:D85) -> 34.750425 | E86: =SUM(E84:E85) -> 34.750425 | F86: =SUM(F84:F85) -> 34.750425 | H86: =SUM(H84:H85) -> 37.12908 | I86: =SUM(I84:I85) -> 37.12908
A87: MP Leche (g/L) | B87: =B76*B69 -> 33.716037 | D87: =D76*D69 -> 32.164828 | E87: =E76*E69 -> 32.164828 | F87: =F76*F69 -> 32.164828 | H87: =H76*H69 -> 32.164746 | I87: =I76*I69 -> 32.164746
A88: MP Nata de suero (g/L) | B88: =B77*B70 -> 0 | D88: =D77*D70 -> 0 | E88: =E77*E70 -> 0 | F88: =F77*F70 -> 0 | H88: =H77*H70 -> 0 | I88: =I77*I70 -> 0
B89: =SUM(B87:B88) -> 33.716037 | D89: =SUM(D87:D88) -> 32.164828 | E89: =SUM(E87:E88) -> 32.164828 | F89: =SUM(F87:F88) -> 32.164828 | H89: =SUM(H87:H88) -> 32.164746 | I89: =SUM(I87:I88) -> 32.164746
A90: Densidad calculada leche en cuba | B90: =SUMPRODUCT(B81:B82,B69:B70) -> 1.0342343 | D90: =SUMPRODUCT(D81:D82,D69:D70) -> 1.0342388 | E90: =SUMPRODUCT(E81:E82,E69:E70) -> 1.0342388 | F90: =SUMPRODUCT(F81:F82,F69:F70) -> 1.0342388 | H90: =SUMPRODUCT(H81:H82,H69:H70) -> 1.0342362 | I90: =SUMPRODUCT(I81:I82,I69:I70) -> 1.0342362
A92: Consumo materia g/kg queso
A93: MG Origen Leche | B93: =+B60*(B84)/B86 -> 329.01325 | D93: =+D60*(D84)/D86 -> 308.19248 | E93: =+E60*(E84)/E86 -> 321.88992 | F93: =+F60*(F84)/F86 -> 321.88992 | H93: =+H60*(H84)/H86 -> 329.28899 | I93: =+I60*(I84)/I86 -> 329.28899
A94: MP Origen Leche | B94: =+B61*(B87)/B89 -> 285.26149 | D94: =+D61*(D87)/D89 -> 285.26149 | E94: =+E61*(E87)/E89 -> 297.93978 | F94: =+F61*(F87)/F89 -> 297.93978 | H94: =+H61*(H87)/H89 -> 285.26149 | I94: =+I61*(I87)/I89 -> 285.26149
A95: MG Origen Nata Suero | B95: =+B$60*(B85)/B$86 -> 0 | D95: =+D$60*(D85)/D$86 -> 0 | E95: =+E$60*(E85)/E$86 -> 0 | F95: =+F$60*(F85)/F$86 -> 0 | H95: =+H$60*(H85)/H$86 -> 0 | I95: =+I$60*(I85)/I$86 -> 0
A96: MP Origen Nata Suero | B96: =+B$61*(B88)/B$89 -> 0 | D96: =+D$61*(D88)/D$89 -> 0 | E96: =+E$61*(E88)/E$89 -> 0 | F96: =+F$61*(F88)/F$89 -> 0 | H96: =+H$61*(H88)/H$89 -> 0 | I96: =+I$61*(I88)/I$89 -> 0
A97: Precio materia (euros/kg)
A98: MG | B98: =Ejemplo!B31 -> 4.9244985 | D98: =Ejemplo!D31 -> 5.510724 | E98: =Ejemplo!E31 -> 5.510724 | F98: =Ejemplo!F31 -> 5.0359096 | H98: =Ejemplo!H31 -> 5.1576823 | I98: =Ejemplo!I31 -> 4.9287513
A99: MP | B99: =Ejemplo!B32 -> 5.6797897 | D99: =Ejemplo!D32 -> 5.9537082 | E99: =Ejemplo!E32 -> 5.9537082 | F99: =Ejemplo!F32 -> 5.4407255 | H99: =Ejemplo!H32 -> 5.9537233 | I99: =Ejemplo!I32 -> 5.6894588
A100: VALOR MG | B100: =B93*B98/1000 -> 1.6202253 | D100: =D93*D98/1000 -> 1.6983637 | E100: =E93*E98/1000 -> 1.7738465 | F100: =F93*F98/1000 -> 1.6210086 | H100: =H93*H98/1000 -> 1.698368 | I100: =I93*I98/1000 -> 1.6229835
A101: VALOR MP | B101: =B94*B99/1000 -> 1.6202253 | D101: =D94*D99/1000 -> 1.6983637 | E101: =E94*E99/1000 -> 1.7738465 | F101: =F94*F99/1000 -> 1.6210086 | H101: =H94*H99/1000 -> 1.698368 | I101: =I94*I99/1000 -> 1.6229835
A102: Total mat prima | B102: =SUM(B100:B101) -> 3.2404505 | D102: =SUM(D100:D101) -> 3.3967273 | E102: =SUM(E100:E101) -> 3.547693 | F102: =SUM(F100:F101) -> 3.2420171 | H102: =SUM(H100:H101) -> 3.396736 | I102: =SUM(I100:I101) -> 3.245967

Sheet Ejemplo coef G como ESM y no MP
A1: 1. Presupuesto | B1: Mezcla | C1: Vaca | D1: Oveja | E1: Light
A2: Datos del producto
A3: EST a salida de sal (%) | B3: 0.5495 | C3: 0.5563 | D3: 0.5635 | E3: 0.5047
A4: MG a saida de sal (%) | B4: 0.3028 | C4: 0.3005 | D4: 0.3093 | E4: 0.2022
A5: Coste de la leche en fabrica
A6: Precio pagado al ganadero (euros/L) | B6: 0.362 | C6: 0.362 | D6: 0.362 | E6: 0.362
A7: Coste transporte + otros recogida (euros/L) | B7: 0.021 | C7: 0.021 | D7: 0.021 | E7: 0.021
A8: Total euros/L | B8: =SUM(B6:B7) -> 0.383 | C8: =SUM(C6:C7) -> 0.383 | D8: =SUM(D6:D7) -> 0.383 | E8: =SUM(E6:E7) -> 0.383
A10: Reparto precio MG leche | B10: 0.5 | C10: 0.5 | D10: 0.5 | E10: 0.5
A11: Reparto precio MP leche (1 - MG) | B11: =1-B10 -> 0.5 | C11: =1-C10 -> 0.5 | D11: =1-D10 -> 0.5 | E11: =1-E10 -> 0.5
A12: Valor MG leche en fábrica (euros/L) | B12: =B38*B19/1000 -> 0.1915 | C12: =C38*C19/1000 -> 0.1915 | D12: =D38*D19/1000 -> 0.1915 | E12: =E38*E19/1000 -> 0.1915
A13: Valor MP leche en fábrica (euros/L) | B13: =B39*B20/1000 -> 0.1915 | C13: =C39*C20/1000 -> 0.1915 | D13: =D39*D20/1000 -> 0.1915 | E13: =E39*E20/1000 -> 0.1915
A14: Datos de materia prima
A15: Composición leche
A16: Materia grasa (% m/m) | B16: 0.0376 | C16: 0.0376 | D16: 0.0376 | E16: 0.0376
A17: Proteinas totales (% m/m) | B17: 0.0326 | C17: 0.0326 | D17: 0.0326 | E17: 0.0326
A18: Factor MG/MP | B18: =B16/B17 -> 1.1533742 | C18: =C16/C17 -> 1.1533742 | D18: =D16/D17 -> 1.1533742 | E18: =E16/E17 -> 1.1533742
A19: Materia grasa (g/L) | B19: =B16*B25 -> 38.887209 | C19: =C16*C25 -> 38.887209 | D19: =D16*D25 -> 38.887209 | E19: =E16*E25 -> 38.887209
A20: Proteinas totales (g/L) | B20: =B17*B25 -> 33.716037 | C20: =C17*C25 -> 33.716037 | D20: =D17*D25 -> 33.716037 | E20: =E17*E25 -> 33.716037
A21: Lactosa | B21: 48 | C21: 48 | D21: 48 | E21: 48
A22: Sales minerales y otros | B22: 9 | C22: 9 | D22: 9 | E22: 9
A23: Agua | B23: =B25-SUM(B19:B22) -> 904.63103 | C23: =C25-SUM(C19:C22) -> 904.63103 | D23: =D25-SUM(D19:D22) -> 904.63103 | E23: =E25-SUM(E19:E22) -> 904.63103
A24: Temperatura a la que se hace la medida (⁰C) | B24: 20 | C24: 20 | D24: 20 | E24: 20
A25: Densidad | B25: =-0.2307*10^(-2)*B24^2-0.2655*B24+1040.51-B16*(-0.478*10^(-4)*B24^2+0.969*10^(-2)*B24+0.967) -> 1034.2343 | C25: =-0.2307*10^(-2)*C24^2-0.2655*C24+1040.51-C16*(-0.478*10^(-4)*C24^2+0.969*10^(-2)*C24+0.967) -> 1034.2343 | D25: =-0.2307*10^(-2)*D24^2-0.2655*D24+1040.51-D16*(-0.478*10^(-4)*D24^2+0.969*10^(-2)*D24+0.967) -> 1034.2343 | E25: =-0.2307*10^(-2)*E24^2-0.2655*E24+1040.51-E16*(-0.478*10^(-4)*E24^2+0.969*10^(-2)*E24+0.967) -> 1034.2343
A26: Composición suero entero (g/L)
A27: EST | B27: 6.5 | C27: 6.5 | D27: 6.5 | E27: 6.5
A28: MG | B28: 4 | C28: 4 | D28: 4 | E28: 4
A29: MP | B29: 8 | C29: 8 | D29: 8 | E29: 8
A30: Lactosa | B30: 48 | C30: 48 | D30: 48 | E30: 48
A31: Sales minerales y otros
A32: Densidad | B32: 1.03 | C32: 1.03 | D32: 1.03 | E32: 1.03
A33: Composición nata suero (g/L)
A34: Materia grasa (% m/m) | B34: 0.43 | C34: 0.43 | D34: 0.43 | E34: 0.43
A35: MG | B35: =B34*B48*1000 -> 423.62953 | C35: =C34*C48*1000 -> 423.62953 | D35: =D34*D48*1000 -> 423.62953 | E35: =E34*E48*1000 -> 423.62953
A36: MP | B36: 5.91 | C36: 5.91 | D36: 5.91 | E36: 5.91
A37: Precio materia (euros/kg)
A38: MG | B38: =B8/B19*B10*1000 -> 4.9244985 | C38: =C8/C19*C10*1000 -> 4.9244985 | D38: =D8/D19*D10*1000 -> 4.9244985 | E38: =E8/E19*E10*1000 -> 4.9244985
A39: MP | B39: =B8/B20*B11*1000 -> 5.6797897 | C39: =C8/C20*C11*1000 -> 5.6797897 | D39: =D8/D20*D11*1000 -> 5.6797897 | E39: =E8/E20*E11*1000 -> 5.6797897
A40: Datos estándar
A41: Receta en volumen (debe sumar 100%)
A42: Leche (%) | B42: 1 | C42: 1 | D42: 1 | E42: 1
A43: Nata de suero de recuperación (%) | B43: =1-B42 -> 0 | C43: =1-C42 -> 0 | D43: =1-D42 -> 0 | E43: =1-E42 -> 0
A44: Coeficientes de recuperación
A45: Coef de recuperación MG
A46: Coef de recuperación MP | B46: 0.9465 | C46: 0.9465 | D46: 0.9465 | E46: 0.9465
A47: Otros datos
A48: Densidad nata (kg/L) | B48: =(-0.2307*10^(-2)*B24^2-0.2655*B24+1040.51-B34*100*(-0.478*10^(-4)*B24^2+0.969*10^(-2)*B24+0.967))/1000 -> 0.98518496 | C48: =(-0.2307*10^(-2)*C24^2-0.2655*C24+1040.51-C34*100*(-0.478*10^(-4)*C24^2+0.969*10^(-2)*C24+0.967))/1000 -> 0.98518496 | D48: =(-0.2307*10^(-2)*D24^2-0.2655*D24+1040.51-D34*100*(-0.478*10^(-4)*D24^2+0.969*10^(-2)*D24+0.967))/1000 -> 0.98518496 | E48: =(-0.2307*10^(-2)*E24^2-0.2655*E24+1040.51-E34*100*(-0.478*10^(-4)*E24^2+0.969*10^(-2)*E24+0.967))/1000 -> 0.98518496
A50: 2. Estándar técnico del producto
A51: Análisis salida sal
A52: EST % | B52: ='Ejemplo coef G como ESM y no MP'!B3 -> 0.5495 | C52: ='Ejemplo coef G como ESM y no MP'!C3 -> 0.5563 | D52: ='Ejemplo coef G como ESM y no MP'!D3 -> 0.5635 | E52: ='Ejemplo coef G como ESM y no MP'!E3 -> 0.5047
A53: MG | B53: ='Ejemplo coef G como ESM y no MP'!B4 -> 0.3028 | C53: ='Ejemplo coef G como ESM y no MP'!C4 -> 0.3005 | D53: ='Ejemplo coef G como ESM y no MP'!D4 -> 0.3093 | E53: ='Ejemplo coef G como ESM y no MP'!E4 -> 0.2022
A54: G/ES % | B54: =B53/B52 -> 0.55104641 | C54: =C53/C52 -> 0.54017616 | D54: =D53/D52 -> 0.54889086 | E54: =E53/E52 -> 0.40063404
A55: HFD | B55: =(1-B52)/(1-B52*B54) -> 0.64615605 | C55: =(1-C52)/(1-C52*C54) -> 0.63431022 | D55: =(1-D52)/(1-D52*D54) -> 0.63196757 | E55: =(1-E52)/(1-E52*E54) -> 0.62083229
A56: ESM | B56: =B52-B53 -> 0.2467 | C56: =C52-C53 -> 0.2558 | D56: =D52-D53 -> 0.2542 | E56: =E52-E53 -> 0.3025
A58: MP en cuba (g/L) | B58: =B96 -> 33.716037 | C58: =C96 -> 33.716037 | D58: =D96 -> 33.716037 | E58: =E96 -> 33.716037
A59: Ratio recuperación MP (Rendimiento MP %) | B59: ='Ejemplo coef G como ESM y no MP'!B46 -> 0.9465 | C59: ='Ejemplo coef G como ESM y no MP'!C46 -> 0.9465 | D59: ='Ejemplo coef G como ESM y no MP'!D46 -> 0.9465 | E59: ='Ejemplo coef G como ESM y no MP'!E46 -> 0.9465
A60: Ratio recuperación MG (%) | B60: =B63/B66 -> 1.0072496 | C60: =C63/C66 -> 0.96403835 | D60: =D63/D66 -> 0.99851535 | E60: =E63/E66 -> 0.54853728
A61: Coef G (ESM queso obtenido a partir de MP leche) | B61: =B59*B58 -> 31.912229 | C61: =C59*C58 -> 31.912229 | D61: =D59*D58 -> 31.912229 | E61: =E59*E58 -> 31.912229
A62: Litraje unitario | B62: =B56*1000/B61 -> 7.7305787 | C62: =C56*1000/C61 -> 8.0157358 | D62: =D56*1000/D61 -> 7.9655983 | E62: =E56*1000/E61 -> 9.4791247
A63: MG teórica en la cuba (g/L) | B63: =B53*1000/B62 -> 39.169125 | C63: =C53*1000/C62 -> 37.48876 | D63: =D53*1000/D62 -> 38.829475 | E63: =E53*1000/E62 -> 21.331084
A64: MG Pérddias brutas suero (g/L) | B64: =B66-B63 -> -0.28191591 | C64: =C66-C63 -> 1.3984483 | D64: =D66-D63 -> 0.057733748 | E64: =E66-E63 -> 17.556125
A65: MG Pérddias brutas suero (%) | B65: =B64/B66 -> -0.0072495796 | C65: =C64/C66 -> 0.035961652 | D65: =D64/D66 -> 0.0014846462 | E65: =E64/E66 -> 0.45146272
A66: MG estándar en la mezcla (g/L) | B66: =B93 -> 38.887209 | C66: =C93 -> 38.887209 | D66: =D93 -> 38.887209 | E66: =E93 -> 38.887209
A67: Consumo MG total leche en cuba | B67: =B66*B62 -> 300.62063 | C67: =C66*C62 -> 311.70959 | D67: =D66*D62 -> 309.75988 | E67: =E66*E62 -> 368.6167
A68: Consumo MP total leche en cuba | B68: =B58*B62 -> 260.64448 | C68: =C58*C62 -> 270.25885 | D68: =D58*D62 -> 268.56841 | E68: =E58*E62 -> 319.59852
A69: MG suero en cuba (g/L) | B69: =+B102/B62 -> 0 | C69: =+C102/C62 -> 0 | D69: =+D102/D62 -> 0 | E69: =+E102/E62 -> 0
A70: MG Pérddas suero neta (g/L) | B70: =B64-B69 -> -0.28191591 | C70: =C64-C69 -> 1.3984483 | D70: =D64-D69 -> 0.057733748 | E70: =E64-E69 -> 17.556125
A71: MG Pérddas suero neta (%) | B71: =+B70/B66 -> -0.0072495796 | C71: =+C70/C66 -> 0.035961652 | D71: =+D70/D66 -> 0.0014846462 | E71: =+E70/E66 -> 0.45146272
A72: MG STD sin nata de suero (g/L) | B72: =+B66-B69 -> 38.887209 | C72: =+C66-C69 -> 38.887209 | D72: =+D66-D69 -> 38.887209 | E72: =+E66-E69 -> 38.887209
A73: Consumo MG (sólo MG comprada) (g/K queso) | B73: =B$72*B$62 -> 300.62063 | C73: =C$72*C$62 -> 311.70959 | D73: =D$72*D$62 -> 309.75988 | E73: =E$72*E$62 -> 368.6167
A74: Consumo MP (sólo MP comprada) (g/K queso) | B74: =B$58*B$62 -> 260.64448 | C74: =C$58*C$62 -> 270.25885 | D74: =D$58*D$62 -> 268.56841 | E74: =E$58*E$62 -> 319.59852
A75: Receta
A76: % Leche | B76: ='Ejemplo coef G como ESM y no MP'!B42 -> 1 | C76: ='Ejemplo coef G como ESM y no MP'!C42 -> 1 | D76: ='Ejemplo coef G como ESM y no MP'!D42 -> 1 | E76: ='Ejemplo coef G como ESM y no MP'!E42 -> 1
A77: % Nata de suero | B77: ='Ejemplo coef G como ESM y no MP'!B43 -> 0 | C77: ='Ejemplo coef G como ESM y no MP'!C43 -> 0 | D77: ='Ejemplo coef G como ESM y no MP'!D43 -> 0 | E77: ='Ejemplo coef G como ESM y no MP'!E43 -> 0
B78: =SUM(B76:B77) -> 1 | C78: =SUM(C76:C77) -> 1 | D78: =SUM(D76:D77) -> 1 | E78: =SUM(E76:E77) -> 1
A79: Composición leche
A80: MG Leche (g/L) | B80: ='Ejemplo coef G como ESM y no MP'!B19 -> 38.887209 | C80: ='Ejemplo coef G como ESM y no MP'!C19 -> 38.887209 | D80: ='Ejemplo coef G como ESM y no MP'!D19 -> 38.887209 | E80: ='Ejemplo coef G como ESM y no MP'!E19 -> 38.887209
A81: MG Nata de Suero (g/L) | B81: ='Ejemplo coef G como ESM y no MP'!B35 -> 423.62953 | C81: ='Ejemplo coef G como ESM y no MP'!C35 -> 423.62953 | D81: ='Ejemplo coef G como ESM y no MP'!D35 -> 423.62953 | E81: ='Ejemplo coef G como ESM y no MP'!E35 -> 423.62953
A83: MP Leche (g/L) | B83: ='Ejemplo coef G como ESM y no MP'!B20 -> 33.716037 | C83: ='Ejemplo coef G como ESM y no MP'!C20 -> 33.716037 | D83: ='Ejemplo coef G como ESM y no MP'!D20 -> 33.716037 | E83: ='Ejemplo coef G como ESM y no MP'!E20 -> 33.716037
A84: MP Nata de suero (g/L) | B84: ='Ejemplo coef G como ESM y no MP'!B36 -> 5.91 | C84: ='Ejemplo coef G como ESM y no MP'!C36 -> 5.91 | D84: ='Ejemplo coef G como ESM y no MP'!D36 -> 5.91 | E84: ='Ejemplo coef G como ESM y no MP'!E36 -> 5.91
A86: Ratio MG/MP leche | B86: =+B93/B96 -> 1.1533742 | C86: =+C93/C96 -> 1.1533742 | D86: =+D93/D96 -> 1.1533742 | E86: =+E93/E96 -> 1.1533742
A88: Densidad Leche | B88: ='Ejemplo coef G como ESM y no MP'!B25/1000 -> 1.0342343 | C88: ='Ejemplo coef G como ESM y no MP'!C25/1000 -> 1.0342343 | D88: ='Ejemplo coef G como ESM y no MP'!D25/1000 -> 1.0342343 | E88: ='Ejemplo coef G como ESM y no MP'!E25/1000 -> 1.0342343
A89: Densidad Nata de suero | B89: ='Ejemplo coef G como ESM y no MP'!B48 -> 0.98518496 | C89: ='Ejemplo coef G como ESM y no MP'!C48 -> 0.98518496 | D89: ='Ejemplo coef G como ESM y no MP'!D48 -> 0.98518496 | E89: ='Ejemplo coef G como ESM y no MP'!E48 -> 0.98518496
A90: Leche en cubas
A91: MG Leche (g/L) | B91: =(B80*B76) -> 38.887209 | C91: =(C80*C76) -> 38.887209 | D91: =(D80*D76) -> 38.887209 | E91: =(E80*E76) -> 38.887209
A92: MG Nata de suero (g/L) | B92: =(B81*B77) -> 0 | C92: =(C81*C77) -> 0 | D92: =(D81*D77) -> 0 | E92: =(E81*E77) -> 0
B93: =SUM(B91:B92) -> 38.887209 | C93: =SUM(C91:C92) -> 38.887209 | D93: =SUM(D91:D92) -> 38.887209 | E93: =SUM(E91:E92) -> 38.887209
A94: MP Leche (g/L) | B94: =B83*B76 -> 33.716037 | C94: =C83*C76 -> 33.716037 | D94: =D83*D76 -> 33.716037 | E94: =E83*E76 -> 33.716037
A95: MP Nata de suero (g/L) | B95: =B84*B77 -> 0 | C95: =C84*C77 -> 0 | D95: =D84*D77 -> 0 | E95: =E84*E77 -> 0
B96: =SUM(B94:B95) -> 33.716037 | C96: =SUM(C94:C95) -> 33.716037 | D96: =SUM(D94:D95) -> 33.716037 | E96: =SUM(E94:E95) -> 33.716037
A97: Densidad calculada leche en cuba | B97: =SUMPRODUCT(B88:B89,B76:B77) -> 1.0342343 | C97: =SUMPRODUCT(C88:C89,C76:C77) -> 1.0342343 | D97: =SUMPRODUCT(D88:D89,D76:D77) -> 1.0342343 | E97: =SUMPRODUCT(E88:E89,E76:E77) -> 1.0342343
A99: Consumo materia g/kg queso
A100: MG Origen Leche | B100: =+B67*(B91)/B93 -> 300.62063 | C100: =+C67*(C91)/C93 -> 311.70959 | D100: =+D67*(D91)/D93 -> 309.75988 | E100: =+E67*(E91)/E93 -> 368.6167
A101: MP Origen Leche | B101: =+B68*(B94)/B96 -> 260.64448 | C101: =+C68*(C94)/C96 -> 270.25885 | D101: =+D68*(D94)/D96 -> 268.56841 | E101: =+E68*(E94)/E96 -> 319.59852
A102: MG Origen Nata Suero | B102: =+B$67*(B92)/B$93 -> 0 | C102: =+C$67*(C92)/C$93 -> 0 | D102: =+D$67*(D92)/D$93 -> 0 | E102: =+E$67*(E92)/E$93 -> 0
A103: MP Origen Nata Suero | B103: =+B$68*(B95)/B$96 -> 0 | C103: =+C$68*(C95)/C$96 -> 0 | D103: =+D$68*(D95)/D$96 -> 0 | E103: =+E$68*(E95)/E$96 -> 0
A104: Precio materia (euros/kg)
A105: MG | B105: ='Ejemplo coef G como ESM y no MP'!B38 -> 4.9244985 | C105: ='Ejemplo coef G como ESM y no MP'!C38 -> 4.9244985 | D105: ='Ejemplo coef G como ESM y no MP'!D38 -> 4.9244985 | E105: ='Ejemplo coef G como ESM y no MP'!E38 -> 4.9244985
A106: MP | B106: ='Ejemplo coef G como ESM y no MP'!B39 -> 5.6797897 | C106: ='Ejemplo coef G como ESM y no MP'!C39 -> 5.6797897 | D106: ='Ejemplo coef G como ESM y no MP'!D39 -> 5.6797897 | E106: ='Ejemplo coef G como ESM y no MP'!E39 -> 5.6797897
A107: VALOR MG | B107: =B100*B105/1000 -> 1.4804058 | C107: =C100*C105/1000 -> 1.5350134 | D107: =D100*D105/1000 -> 1.5254121 | E107: =E100*E105/1000 -> 1.8152524
...
