Workbook
Name _100_PV: #REF!
Name _100_SVI: #REF!
Name _1000_XM: #REF!
Name _145110: #REF!
Name _162460: [4]STEPHAN!$B$2:$P$71
Name _170_LIGHT: #REF!
Name _170_PV: #REF!
Name _171015: #REF!
Name _171064: #REF!
Name _171066: #REF!
Name _171068: #REF!
Name _171510: #REF!
Name _171562: #REF!
Name _172012: #REF!
Name _172020: #REF!
Name _172022: #REF!
Name _172062: #REF!
Name _172510: [4]STEPHAN!$B$2:$Q$71
Name _172610: [4]STEPHAN!$B$2:$Q$71
Name _176072: #REF!
Name A_impresión_IM: #REF!
Name bd: #REF!
Name bof: "ComboBox1"
Name dd: #REF!
Name EssLatest: "JAN"
Name EssLatest_10: "JAN"
Name EssLatest_11: "JAN"
Name EssLatest_12: "JAN"
Name EssLatest_13: "JAN"
Name EssLatest_14: "JAN"
Name EssLatest_15: "JAN"
Name EssLatest_16: "JAN"
Name EssLatest_18: "JAN"
Name EssLatest_2: "JANN0"
Name EssLatest_20: "YTDMM01"
Name EssLatest_25: "YTDMM01"
Name EssLatest_26: "YTDMM01"
Name EssLatest_3: "JANN0"
Name EssLatest_38: "JAN"
Name EssLatest_39: "JAN"
Name EssLatest_4: "JANN0"
Name EssLatest_47: "JAN"
Name EssLatest_48: "JAN"
Name EssLatest_5: "JANN0"
Name EssLatest_6: "YTDMM01"
Name EssLatest_7: "YTDMM01"
Name EssLatest_8: "YTDMM01"
Name EssLatest_9: "JAN"
Name EssOptions_10: "A3000001100130001011001101020_01 00"
Name EssOptions_11: "A3000001100130001011001101020_01 00"
Name EssOptions_12: "A3000001100130001011001101020_01 00"
Name EssOptions_13: "A3000001100130001011001101020_01 00"
Name EssOptions_14: "A3000001100130001011001101020_01 00"
Name EssOptions_15: "A3000001100130001011001101020_01 00"
Name EssOptions_16: "A3000001100130001011001101020_01 00"
Name EssOptions_18: "A3000001100130001011001101020_01 00"
Name EssOptions_2: "A1100000010121000011001111120_01000"
Name EssOptions_20: "A3100000000110001011011111020_01000"
Name EssOptions_25: "A3100000000130000000011100020_01000"
Name EssOptions_26: "A3100000000110001011011111020_01000"

Sheet Std con datos de csv fab_queso
A1: 1. Presupuesto | B1: Mezcla | C1: Vaca | D1: Oveja | E1: Bajo en MG
A2: Datos del producto
A3: EST a salida de sal (%) | B3: 0.5495 | C3: 0.5563 | D3: 0.5635 | E3: 0.5047
A4: MG a saida de sal (%) | B4: 0.3028 | C4: 0.3005 | D4: 0.3093 | E4: 0.2022
A5: Coste de la leche en fabrica
A6: Precio pagado al ganadero (euros/L) | B6: 0.494 | C6: 0.494 | D6: 1.375 | E6: 0.494
A7: Coste transporte + otros recogida (euros/L) | B7: 0.021 | C7: 0.021 | D7: 0.021 | E7: 0.021
A8: Total euros/L | B8: =SUM(B6:B7) -> 0.515 | C8: =SUM(C6:C7) -> 0.515 | D8: =SUM(D6:D7) -> 1.396 | E8: =SUM(E6:E7) -> 0.515
A10: Reparto precio MG leche | B10: 0.5 | C10: 0.5 | D10: 0.5 | E10: 0.5
A11: Reparto precio MP leche (1 - MG) | B11: =1-B10 -> 0.5 | C11: =1-C10 -> 0.5 | D11: =1-D10 -> 0.5 | E11: =1-E10 -> 0.5
A12: Valor MG leche en fábrica (euros/L) | B12: =B38*B19/1000 -> 0.2575 | C12: =C38*C19/1000 -> 0.2575 | D12: =D38*D19/1000 -> 0.698 | E12: =E38*E19/1000 -> 0.2575
A13: Valor MP leche en fábrica (euros/L) | B13: =B39*B20/1000 -> 0.2575 | C13: =C39*C20/1000 -> 0.2575 | D13: =D39*D20/1000 -> 0.698 | E13: =E39*E20/1000 -> 0.2575
A14: Datos de materia prima
A15: Composición leche
A16: Materia grasa (% m/m) | B16: 0.04 | C16: 0.0376 | D16: 0.0687 | E16: 0.024
A17: Proteinas totales (% m/m) | B17: 0.030993046 | C17: 0.03072033 | D17: 0.055090424 | E17: 0.032548054
A18: Factor MG/MP | B18: =B16/B17 -> 1.2906121 | C18: =C16/C17 -> 1.2239452 | D18: =D16/D17 -> 1.2470407 | E18: =E16/E17 -> 0.73737128
A19: Materia grasa (g/L) | B19: =B16*B25 -> 41.369261 | C19: =C16*C25 -> 38.887209 | D19: =D16*D25 -> 71.049455 | E19: =E16*E25 -> 24.821995
A20: Proteinas totales (g/L) | B20: =B17*B25 -> 32.053986 | C20: =C17*C25 -> 31.772018 | D20: =D17*D25 -> 56.974449 | E20: =E17*E25 -> 33.662818
A21: Lactosa | B21: 48 | C21: 48 | D21: 48 | E21: 48
A22: Sales minerales y otros | B22: 9 | C22: 9 | D22: 9 | E22: 9
A23: Agua | B23: =B25-SUM(B19:B22) -> 903.80829 | C23: =C25-SUM(C19:C22) -> 906.57505 | D23: =D25-SUM(D19:D22) -> 849.17486 | E23: =E25-SUM(E19:E22) -> 918.76499
A24: Temperatura a la que se hace la medida (⁰C) | B24: 20 | C24: 20 | D24: 20 | E24: 20
A25: Densidad | B25: =-0.2307*10^(-2)*B24^2-0.2655*B24+1040.51-B16*(-0.478*10^(-4)*B24^2+0.969*10^(-2)*B24+0.967) -> 1034.2315 | C25: =-0.2307*10^(-2)*C24^2-0.2655*C24+1040.51-C16*(-0.478*10^(-4)*C24^2+0.969*10^(-2)*C24+0.967) -> 1034.2343 | D25: =-0.2307*10^(-2)*D24^2-0.2655*D24+1040.51-D16*(-0.478*10^(-4)*D24^2+0.969*10^(-2)*D24+0.967) -> 1034.1988 | E25: =-0.2307*10^(-2)*E24^2-0.2655*E24+1040.51-E16*(-0.478*10^(-4)*E24^2+0.969*10^(-2)*E24+0.967) -> 1034.2498
A26: Composición suero entero (g/L)
A27: EST | B27: 6.5 | C27: 6.5 | D27: 6.5 | E27: 6.5
A28: MG | B28: 4 | C28: 4 | D28: 4 | E28: 4
A29: MP | B29: 8 | C29: 8 | D29: 8 | E29: 8
A30: Lactosa | B30: 48 | C30: 48 | D30: 48 | E30: 48
A31: Sales minerales y otros
A32: Densidad | B32: 1.03 | C32: 1.03 | D32: 1.03 | E32: 1.03
A33: Composición nata suero (g/L)
A34: Materia grasa (% m/m) | B34: 0.43 | C34: 0.43 | D34: 0.43 | E34: 0.43
A35: MG | B35: =B34*B48*1000 -> 423.62953 | C35: =C34*C48*1000 -> 423.62953 | D35: =D34*D48*1000 -> 423.62953 | E35: =E34*E48*1000 -> 423.62953
A36: MP | B36: 5.91 | C36: 5.91 | D36: 5.91 | E36: 5.91
A37: Precio materia (euros/kg)
A38: MG | B38: =B8/B19*B10*1000 -> 6.2244283 | C38: =C8/C19*C10*1000 -> 6.6217147 | D38: =D8/D19*D10*1000 -> 9.8241429 | E38: =E8/E19*E10*1000 -> 10.373864
A39: MP | B39: =B8/B20*B11*1000 -> 8.0333224 | C39: =C8/C20*C11*1000 -> 8.1046159 | D39: =D8/D20*D11*1000 -> 12.251106 | E39: =E8/E20*E11*1000 -> 7.6493893
A40: Datos estándar
A41: Receta en volumen (debe sumar 100%)
A42: Leche (%) | B42: 1 | C42: 1 | D42: 1 | E42: 1
A43: Nata de suero de recuperación (%) | B43: =1-B42 -> 0 | C43: =1-C42 -> 0 | D43: =1-D42 -> 0 | E43: =1-E42 -> 0
A44: Coeficientes de recuperación
A45: Coef de recuperación MG
A46: Coef de recuperación MP | B46: 0.9465 | C46: 0.9465 | D46: 0.9465 | E46: 0.9465
A47: Otros datos
A48: Densidad nata (kg/L) | B48: =(-0.2307*10^(-2)*B24^2-0.2655*B24+1040.51-B34*100*(-0.478*10^(-4)*B24^2+0.969*10^(-2)*B24+0.967))/1000 -> 0.98518496 | C48: =(-0.2307*10^(-2)*C24^2-0.2655*C24+1040.51-C34*100*(-0.478*10^(-4)*C24^2+0.969*10^(-2)*C24+0.967))/1000 -> 0.98518496 | D48: =(-0.2307*10^(-2)*D24^2-0.2655*D24+1040.51-D34*100*(-0.478*10^(-4)*D24^2+0.969*10^(-2)*D24+0.967))/1000 -> 0.98518496 | E48: =(-0.2307*10^(-2)*E24^2-0.2655*E24+1040.51-E34*100*(-0.478*10^(-4)*E24^2+0.969*10^(-2)*E24+0.967))/1000 -> 0.98518496
A50: 2. Estándar técnico del producto
A51: Análisis salida sal
A52: EST % | B52: ='Std con datos de csv fab_queso'!B3 -> 0.5495 | C52: ='Std con datos de csv fab_queso'!C3 -> 0.5563 | D52: ='Std con datos de csv fab_queso'!D3 -> 0.5635 | E52: ='Std con datos de csv fab_queso'!E3 -> 0.5047
A53: MG | B53: ='Std con datos de csv fab_queso'!B4 -> 0.3028 | C53: ='Std con datos de csv fab_queso'!C4 -> 0.3005 | D53: ='Std con datos de csv fab_queso'!D4 -> 0.3093 | E53: ='Std con datos de csv fab_queso'!E4 -> 0.2022
A54: G/ES % | B54: =B53/B52 -> 0.55104641 | C54: =C53/C52 -> 0.54017616 | D54: =D53/D52 -> 0.54889086 | E54: =E53/E52 -> 0.40063404
A55: HFD | B55: =(1-B52)/(1-B52*B54) -> 0.64615605 | C55: =(1-C52)/(1-C52*C54) -> 0.63431022 | D55: =(1-D52)/(1-D52*D54) -> 0.63196757 | E55: =(1-E52)/(1-E52*E54) -> 0.62083229
A56: ESM | B56: =B52-B53 -> 0.2467 | C56: =C52-C53 -> 0.2558 | D56: =D52-D53 -> 0.2542 | E56: =E52-E53 -> 0.3025
A58: MP en cuba (g/L) | B58: =B96 -> 32.053986 | C58: =C96 -> 31.772018 | D58: =D96 -> 56.974449 | E58: =E96 -> 33.662818
A59: Ratio recuperación MP (Rendimiento MP %) | B59: 0.9678 | C59: 0.9528 | D59: 0.9348 | E59: 0.9733
A60: Ratio recuperación MG (%) | B60: =B63/B66 -> 0.9204 | C60: =C63/C66 -> 0.9145 | D60: =D63/D66 -> 0.9121 | E60: =E63/E66 -> 0.8823
A61: Coef G (ESM queso obtenido a partir de MP leche) | B61: =B59*B58 -> 31.021847 | C61: =C59*C58 -> 30.272378 | D61: =D59*D58 -> 53.259715 | E61: =E59*E58 -> 32.764021
A62: Litraje unitario | B62: =B56*1000/B61 -> 7.95246 | C62: =C56*1000/C61 -> 8.4499472 | D62: =D56*1000/D61 -> 4.7728382 | E62: =E56*1000/E61 -> 9.2326885
A63: MG teórica en la cuba (g/L) | B63: =B53*1000/B62 -> 38.076268 | C63: =C53*1000/C62 -> 35.562352 | D63: =D53*1000/D62 -> 64.804208 | E63: =E53*1000/E62 -> 21.900446
A64: MG Pérddias brutas suero (g/L) | B64: =B66-B63 -> 3.2929932 | C64: =C66-C63 -> 3.3248563 | D64: =D66-D63 -> 6.2452471 | E64: =E66-E63 -> 2.9215488
A65: MG Pérddias brutas suero (%) | B65: =B64/B66 -> 0.0796 | C65: =C64/C66 -> 0.0855 | D65: =D64/D66 -> 0.0879 | E65: =E64/E66 -> 0.1177
A66: MG estándar en la mezcla (g/L) | B66: =B93 -> 41.369261 | C66: =C93 -> 38.887209 | D66: =D93 -> 71.049455 | E66: =E93 -> 24.821995
A67: Consumo MG total leche en cuba | B67: =B66*B62 -> 328.9874 | C67: =C66*C62 -> 328.59486 | D67: =D66*D62 -> 339.10755 | E67: =E66*E62 -> 229.17375
A68: Consumo MP total leche en cuba | B68: =B58*B62 -> 254.90804 | C68: =C58*C62 -> 268.47187 | D68: =D58*D62 -> 271.92982 | E68: =E58*E62 -> 310.79832
A69: MG suero en cuba (g/L) | B69: =+B102/B62 -> 0 | C69: =+C102/C62 -> 0 | D69: =+D102/D62 -> 0 | E69: =+E102/E62 -> 0
A70: MG Pérdidas suero neta (g/L) | B70: =B64-B69 -> 3.2929932 | C70: =C64-C69 -> 3.3248563 | D70: =D64-D69 -> 6.2452471 | E70: =E64-E69 -> 2.9215488
A71: MG Pérdidas suero neta (%) | B71: =+B70/B66 -> 0.0796 | C71: =+C70/C66 -> 0.0855 | D71: =+D70/D66 -> 0.0879 | E71: =+E70/E66 -> 0.1177
A72: MG STD sin nata de suero (g/L) | B72: =+B66-B69 -> 41.369261 | C72: =+C66-C69 -> 38.887209 | D72: =+D66-D69 -> 71.049455 | E72: =+E66-E69 -> 24.821995
A73: Consumo MG (sólo MG comprada) (g/K queso) | B73: =B$72*B$62 -> 328.9874 | C73: =C$72*C$62 -> 328.59486 | D73: =D$72*D$62 -> 339.10755 | E73: =E$72*E$62 -> 229.17375
A74: Consumo MP (sólo MP comprada) (g/K queso) | B74: =B$58*B$62 -> 254.90804 | C74: =C$58*C$62 -> 268.47187 | D74: =D$58*D$62 -> 271.92982 | E74: =E$58*E$62 -> 310.79832
A75: Receta
A76: % Leche | B76: ='Std con datos de csv fab_queso'!B42 -> 1 | C76: ='Std con datos de csv fab_queso'!C42 -> 1 | D76: ='Std con datos de csv fab_queso'!D42 -> 1 | E76: ='Std con datos de csv fab_queso'!E42 -> 1
A77: % Nata de suero | B77: ='Std con datos de csv fab_queso'!B43 -> 0 | C77: ='Std con datos de csv fab_queso'!C43 -> 0 | D77: ='Std con datos de csv fab_queso'!D43 -> 0 | E77: ='Std con datos de csv fab_queso'!E43 -> 0
B78: =SUM(B76:B77) -> 1 | C78: =SUM(C76:C77) -> 1 | D78: =SUM(D76:D77) -> 1 | E78: =SUM(E76:E77) -> 1
A79: Composición leche
A80: MG Leche (g/L) | B80: ='Std con datos de csv fab_queso'!B19 -> 41.369261 | C80: ='Std con datos de csv fab_queso'!C19 -> 38.887209 | D80: ='Std con datos de csv fab_queso'!D19 -> 71.049455 | E80: ='Std con datos de csv fab_queso'!E19 -> 24.821995
A81: MG Nata de Suero (g/L) | B81: ='Std con datos de csv fab_queso'!B35 -> 423.62953 | C81: ='Std con datos de csv fab_queso'!C35 -> 423.62953 | D81: ='Std con datos de csv fab_queso'!D35 -> 423.62953 | E81: ='Std con datos de csv fab_queso'!E35 -> 423.62953
A83: MP Leche (g/L) | B83: ='Std con datos de csv fab_queso'!B20 -> 32.053986 | C83: ='Std con datos de csv fab_queso'!C20 -> 31.772018 | D83: ='Std con datos de csv fab_queso'!D20 -> 56.974449 | E83: ='Std con datos de csv fab_queso'!E20 -> 33.662818
A84: MP Nata de suero (g/L) | B84: ='Std con datos de csv fab_queso'!B36 -> 5.91 | C84: ='Std con datos de csv fab_queso'!C36 -> 5.91 | D84: ='Std con datos de csv fab_queso'!D36 -> 5.91 | E84: ='Std con datos de csv fab_queso'!E36 -> 5.91
A86: Ratio MG/MP leche | B86: =+B93/B96 -> 1.2906121 | C86: =+C93/C96 -> 1.2239452 | D86: =+D93/D96 -> 1.2470407 | E86: =+E93/E96 -> 0.73737128
A88: Densidad Leche | B88: ='Std con datos de csv fab_queso'!B25/1000 -> 1.0342315 | C88: ='Std con datos de csv fab_queso'!C25/1000 -> 1.0342343 | D88: ='Std con datos de csv fab_queso'!D25/1000 -> 1.0341988 | E88: ='Std con datos de csv fab_queso'!E25/1000 -> 1.0342498
A89: Densidad Nata de suero | B89: ='Std con datos de csv fab_queso'!B48 -> 0.98518496 | C89: ='Std con datos de csv fab_queso'!C48 -> 0.98518496 | D89: ='Std con datos de csv fab_queso'!D48 -> 0.98518496 | E89: ='Std con datos de csv fab_queso'!E48 -> 0.98518496
A90: Leche en cubas
A91: MG Leche (g/L) | B91: =(B80*B76) -> 41.369261 | C91: =(C80*C76) -> 38.887209 | D91: =(D80*D76) -> 71.049455 | E91: =(E80*E76) -> 24.821995
A92: MG Nata de suero (g/L) | B92: =(B81*B77) -> 0 | C92: =(C81*C77) -> 0 | D92: =(D81*D77) -> 0 | E92: =(E81*E77) -> 0
B93: =SUM(B91:B92) -> 41.369261 | C93: =SUM(C91:C92) -> 38.887209 | D93: =SUM(D91:D92) -> 71.049455 | E93: =SUM(E91:E92) -> 24.821995
A94: MP Leche (g/L) | B94: =B83*B76 -> 32.053986 | C94: =C83*C76 -> 31.772018 | D94: =D83*D76 -> 56.974449 | E94: =E83*E76 -> 33.662818
A95: MP Nata de suero (g/L) | B95: =B84*B77 -> 0 | C95: =C84*C77 -> 0 | D95: =D84*D77 -> 0 | E95: =E84*E77 -> 0
B96: =SUM(B94:B95) -> 32.053986 | C96: =SUM(C94:C95) -> 31.772018 | D96: =SUM(D94:D95) -> 56.974449 | E96: =SUM(E94:E95) -> 33.662818
A97: Densidad calculada leche en cuba | B97: =SUMPRODUCT(B88:B89,B76:B77) -> 1.0342315 | C97: =SUMPRODUCT(C88:C89,C76:C77) -> 1.0342343 | D97: =SUMPRODUCT(D88:D89,D76:D77) -> 1.0341988 | E97: =SUMPRODUCT(E88:E89,E76:E77) -> 1.0342498
A99: Consumo materia g/kg queso
A100: MG Origen Leche | B100: =+B67*(B91)/B93 -> 328.9874 | C100: =+C67*(C91)/C93 -> 328.59486 | D100: =+D67*(D91)/D93 -> 339.10755 | E100: =+E67*(E91)/E93 -> 229.17375
A101: MP Origen Leche | B101: =+B68*(B94)/B96 -> 254.90804 | C101: =+C68*(C94)/C96 -> 268.47187 | D101: =+D68*(D94)/D96 -> 271.92982 | E101: =+E68*(E94)/E96 -> 310.79832
A102: MG Origen Nata Suero | B102: =+B$67*(B92)/B$93 -> 0 | C102: =+C$67*(C92)/C$93 -> 0 | D102: =+D$67*(D92)/D$93 -> 0 | E102: =+E$67*(E92)/E$93 -> 0
A103: MP Origen Nata Suero | B103: =+B$68*(B95)/B$96 -> 0 | C103: =+C$68*(C95)/C$96 -> 0 | D103: =+D$68*(D95)/D$96 -> 0 | E103: =+E$68*(E95)/E$96 -> 0
A104: Precio materia (euros/kg)
A105: MG | B105: ='Std con datos de csv fab_queso'!B38 -> 6.2244283 | C105: ='Std con datos de csv fab_queso'!C38 -> 6.6217147 | D105: ='Std con datos de csv fab_queso'!D38 -> 9.8241429 | E105: ='Std con datos de csv fab_queso'!E38 -> 10.373864
A106: MP | B106: ='Std con datos de csv fab_queso'!B39 -> 8.0333224 | C106: ='Std con datos de csv fab_queso'!C39 -> 8.1046159 | D106: ='Std con datos de csv fab_queso'!D39 -> 12.251106 | E106: ='Std con datos de csv fab_queso'!E39 -> 7.6493893
A107: VALOR MG | B107: =B100*B105/1000 -> 2.0477585 | C107: =C100*C105/1000 -> 2.1758614 | D107: =D100*D105/1000 -> 3.3314411 | E107: =E100*E105/1000 -> 2.3774173
...

Sheet Std con datos de csv fab_qu (2)
B1: Ejemplo
A2: Datos del producto
A3: EST a salida de sal (%) | B3: 0.55
A4: MG a saida de sal (%) | B4: 0.28
A5: Datos de materia prima
A6: Composición leche
A7: Materia grasa (% m/m) | B7: 0.0334
A8: Proteinas totales (% m/m) | B8: 0.0311
A9: Factor MG/MP | B9: =B7/B8 -> 1.073955
A10: Materia grasa (g/L) | B10: =B7*B16 -> 34.543585
A11: Proteinas totales (g/L) | B11: =B8*B16 -> 32.164835
A12: Lactosa | B12: 48
A13: Sales minerales y otros | B13: 9
A14: Agua | B14: =B16-SUM(B10:B13) -> 910.53065
A15: Temperatura a la que se hace la medida (⁰C) | B15: 20
A16: Densidad | B16: =-0.2307*10^(-2)*B15^2-0.2655*B15+1040.51-B7*(-0.478*10^(-4)*B15^2+0.969*10^(-2)*B15+0.967) -> 1034.2391
A17: Composición suero entero (g/L)
A18: EST | B18: 6.5
A19: MG | B19: 4
A20: MP | B20: 8
A21: Lactosa | B21: 48
A22: Sales minerales y otros
A23: Densidad | B23: 1.03
A24: Composición nata suero (g/L)
A25: Materia grasa (% m/m) | B25: 0.43
A26: MG | B26: =B25*B36*1000 -> 423.62953
A27: MP | B27: 5.91
A28: Datos estándar
A29: Receta en volumen (debe sumar 100%)
A30: Leche (%) | B30: 1
A31: Nata de suero de recuperación (%) | B31: =1-B30 -> 0
A32: Coeficientes de recuperación
A33: Coef de recuperación MG
A34: Coef de recuperación MP | B34: 0.9465
A35: Otros datos
A36: Densidad nata (kg/L) | B36: =(-0.2307*10^(-2)*B15^2-0.2655*B15+1040.51-B25*100*(-0.478*10^(-4)*B15^2+0.969*10^(-2)*B15+0.967))/1000 -> 0.98518496
A38: 2. Estándar técnico del producto
A39: Análisis salida sal
A40: EST % | B40: ='Std con datos de csv fab_qu (2)'!B3 -> 0.55
A41: MG | B41: ='Std con datos de csv fab_qu (2)'!B4 -> 0.28
A42: G/ES % | B42: =B41/B40 -> 0.50909091
A43: HFD | B43: =(1-B40)/(1-B40*B42) -> 0.625
A44: ESM | B44: =B40-B41 -> 0.27
A46: MP en cuba (g/L) | B46: =B84 -> 32.164835
A47: Ratio recuperación MP (Rendimiento MP %) | B47: 0.9678
A48: Ratio recuperación MG (%) | B48: =B51/B54 -> 0.9345312
A49: Coef G (ESM queso obtenido a partir de MP leche) | B49: =B47*B46 -> 31.129127
A50: Litraje unitario | B50: =B44*1000/B49 -> 8.6735486
A51: MG teórica en la cuba (g/L) | B51: =B41*1000/B50 -> 32.282058
A52: MG Pérddias brutas suero (g/L) | B52: =B54-B51 -> 2.2615269
A53: MG Pérddias brutas suero (%) | B53: =B52/B54 -> 0.065468796
A54: MG estándar en la mezcla (g/L) | B54: =B81 -> 34.543585
A55: Consumo MG total leche en cuba | B55: =B54*B50 -> 299.61546
A56: Consumo MP total leche en cuba | B56: =B46*B50 -> 278.98326
A57: MG suero en cuba (g/L) | B57: =+B90/B50 -> 0
A58: MG Pérdidas suero neta (g/L) | B58: =B52-B57 -> 2.2615269
A59: MG Pérdidas suero neta (%) | B59: =+B58/B54 -> 0.065468796
A60: MG STD sin nata de suero (g/L) | B60: =+B54-B57 -> 34.543585
A61: Consumo MG (sólo MG comprada) (g/K queso) | B61: =B$60*B$50 -> 299.61546
A62: Consumo MP (sólo MP comprada) (g/K queso) | B62: =B$46*B$50 -> 278.98326
A63: Receta
A64: % Leche | B64: ='Std con datos de csv fab_qu (2)'!B30 -> 1
A65: % Nata de suero | B65: ='Std con datos de csv fab_qu (2)'!B31 -> 0
B66: =SUM(B64:B65) -> 1
A67: Composición leche
A68: MG Leche (g/L) | B68: ='Std con datos de csv fab_qu (2)'!B10 -> 34.543585
A69: MG Nata de Suero (g/L) | B69: ='Std con datos de csv fab_qu (2)'!B26 -> 423.62953
A71: MP Leche (g/L) | B71: ='Std con datos de csv fab_qu (2)'!B11 -> 32.164835
A72: MP Nata de suero (g/L) | B72: ='Std con datos de csv fab_qu (2)'!B27 -> 5.91
A74: Ratio MG/MP leche | B74: =+B81/B84 -> 1.073955
A76: Densidad Leche | B76: ='Std con datos de csv fab_qu (2)'!B16/1000 -> 1.0342391
A77: Densidad Nata de suero | B77: ='Std con datos de csv fab_qu (2)'!B36 -> 0.98518496
A78: Leche en cubas
A79: MG Leche (g/L) | B79: =(B68*B64) -> 34.543585
A80: MG Nata de suero (g/L) | B80: =(B69*B65) -> 0
B81: =SUM(B79:B80) -> 34.543585
A82: MP Leche (g/L) | B82: =B71*B64 -> 32.164835
A83: MP Nata de suero (g/L) | B83: =B72*B65 -> 0
B84: =SUM(B82:B83) -> 32.164835
A85: Densidad calculada leche en cuba | B85: =SUMPRODUCT(B76:B77,B64:B65) -> 1.0342391
A87: Consumo materia g/kg queso
A88: MG Origen Leche | B88: =+B55*(B79)/B81 -> 299.61546
A89: MP Origen Leche | B89: =+B56*(B82)/B84 -> 278.98326
A90: MG Origen Nata Suero | B90: =+B$55*(B80)/B$81 -> 0
A91: MP Origen Nata Suero | B91: =+B$56*(B83)/B$84 -> 0
